Metadata-Version: 2.0
Name: volition-server-management
Version: 1.0.0
Summary: A set of server management tools used by Volition.
Home-page: https://gitlab.com/Volition/server-management/
Author: Volition
Author-email: technical@wearevolition.co
License: UNKNOWN
Platform: UNKNOWN
Requires-Python: >=3
Requires-Dist: django
Requires-Dist: fabric3
Requires-Dist: requests
Requires-Dist: fabric3-virtualenv
Provides-Extra: testing
Requires-Dist: astroid (==1.5.3); extra == 'testing'
Requires-Dist: coveralls; extra == 'testing'
Requires-Dist: pytest; extra == 'testing'
Requires-Dist: pytest-cov; extra == 'testing'
Requires-Dist: pytest-django; extra == 'testing'
Requires-Dist: pylint (==1.7.5); extra == 'testing'
Requires-Dist: pylint-django (==0.7.2); extra == 'testing'
Requires-Dist: pylint-mccabe (==0.1.3); extra == 'testing'
Requires-Dist: isort (==4.2.15); extra == 'testing'
